MANIFEST.in
README.md
nativeextractormodule.c
setup.py
./nativeextractor/include/nativeextractor/common.h
./nativeextractor/include/nativeextractor/csv_parser.h
./nativeextractor/include/nativeextractor/extractor.h
./nativeextractor/include/nativeextractor/finite_automaton.h
./nativeextractor/include/nativeextractor/miner.h
./nativeextractor/include/nativeextractor/ner.h
./nativeextractor/include/nativeextractor/occurrence.h
./nativeextractor/include/nativeextractor/pair.h
./nativeextractor/include/nativeextractor/patricia.h
./nativeextractor/include/nativeextractor/patricia_miner.h
./nativeextractor/include/nativeextractor/regex_generator.h
./nativeextractor/include/nativeextractor/stream.h
./nativeextractor/include/nativeextractor/terminal.h
./nativeextractor/include/nativeextractor/unicode.h
./nativeextractor/src/csv_parser.c
./nativeextractor/src/extractor.c
./nativeextractor/src/finite_automaton.c
./nativeextractor/src/miner.c
./nativeextractor/src/ner.c
./nativeextractor/src/occurrence.c
./nativeextractor/src/pair.c
./nativeextractor/src/patricia.c
./nativeextractor/src/patricia_miner.c
./nativeextractor/src/regex_generator.c
./nativeextractor/src/stream.c
./nativeextractor/src/unicode.c
pynativeextractor/__init__.py
pynativeextractor/extractor.py
pynativeextractor/patricia.py
pynativeextractor.egg-info/PKG-INFO
pynativeextractor.egg-info/SOURCES.txt
pynativeextractor.egg-info/dependency_links.txt
pynativeextractor.egg-info/requires.txt
pynativeextractor.egg-info/top_level.txt