Metadata-Version: 2.1
Name: pynativeextractor
Version: 1.0.15
Summary: Python binding for nativeextractor
Home-page: https://github.com/SpongeData-cz/pynativeextractor
Author: SpongeData s.r.o.
Author-email: info@spongedata.cz
License: UNKNOWN
Project-URL: Bug Tracker, https://github.com/SpongeData-cz/pynativeextractor/issues
Platform: UNKNOWN
Classifier: Programming Language :: Python :: 2
Classifier: Programming Language :: Python :: 3
Classifier: License :: OSI Approved :: MIT License
Classifier: Operating System :: POSIX :: Linux
Requires-Python: >=2.7
